jenkinsyamlconfigs/__init__.py
jenkinsyamlconfigs/api.py
jenkinsyamlconfigs/renderer.py
jenkinsyamlconfigs/scripts/__init__.py
jenkinsyamlconfigs/scripts/example.sh
jenkinsyamlconfigs/templates/__init__.py
jenkinsyamlconfigs/templates/job.xml
jenkinsyamlconfigs/templates/macros.xml
jenkinsyamlconfigs/templates/builders/__init__.py
jenkinsyamlconfigs/templates/builders/blockable-build-trigger.xml
jenkinsyamlconfigs/templates/builders/build-trigger.xml
jenkinsyamlconfigs/templates/builders/conditional.xml
jenkinsyamlconfigs/templates/builders/copy-artifact.xml
jenkinsyamlconfigs/templates/builders/groovy.xml
jenkinsyamlconfigs/templates/builders/parameterized-build-trigger.xml
jenkinsyamlconfigs/templates/builders/parameterized-trigger.xml
jenkinsyamlconfigs/templates/builders/shell.xml
jenkinsyamlconfigs/templates/builders/system-groovy.xml
jenkinsyamlconfigs/templates/builders/paramFactories/__init__.py
jenkinsyamlconfigs/templates/builders/paramFactories/node-for-label.xml
jenkinsyamlconfigs/templates/builders/params/__init__.py
jenkinsyamlconfigs/templates/builders/params/current-build-params.xml
jenkinsyamlconfigs/templates/builders/params/predefined.xml
jenkinsyamlconfigs/templates/buildWrappers/__init__.py
jenkinsyamlconfigs/templates/buildWrappers/color-output.xml
jenkinsyamlconfigs/templates/buildWrappers/namesetter.xml
jenkinsyamlconfigs/templates/buildWrappers/pyenv.xml
jenkinsyamlconfigs/templates/buildWrappers/timestamper.xml
jenkinsyamlconfigs/templates/conditions/__init__.py
jenkinsyamlconfigs/templates/conditions/bool.xml
jenkinsyamlconfigs/templates/conditions/current-build-status.xml
jenkinsyamlconfigs/templates/conditions/string.xml
jenkinsyamlconfigs/templates/parameters/__init__.py
jenkinsyamlconfigs/templates/parameters/bool.xml
jenkinsyamlconfigs/templates/parameters/choice.xml
jenkinsyamlconfigs/templates/parameters/node-label.xml
jenkinsyamlconfigs/templates/parameters/string.xml
jenkinsyamlconfigs-0.1.0.dist-info/DESCRIPTION.rst
jenkinsyamlconfigs-0.1.0.dist-info/METADATA
jenkinsyamlconfigs-0.1.0.dist-info/metadata.json
jenkinsyamlconfigs-0.1.0.dist-info/namespace_packages.txt
jenkinsyamlconfigs-0.1.0.dist-info/RECORD
jenkinsyamlconfigs-0.1.0.dist-info/top_level.txt
jenkinsyamlconfigs-0.1.0.dist-info/WHEEL
