Metadata-Version: 2.0
Name: jenkinsyamlconfigs
Version: 0.1.0
Summary: Jenkins YAML Configs - Jenkins Configuration as YAML
Home-page: https://github.com/rocktavious/jenkins-yaml-configs
Author: Kyle Rockman
Author-email: kyle.rockman@mac.com
License: The MIT License (MIT)
Requires-Dist: jenkinsapi
Requires-Dist: pyul
